{"skeleton":{"hash":"e3ilpo8X0zRcL7ZtQe+23BM02OI","spine":"3.8.75","images":"E:/VS Code Porject/Client/all png's/symbols_hd","audio":""},"bones":[{"name":"root"},{"name":"shotung_mover","parent":"root","x":4.24,"y":-0.21},{"name":"Gilza_out","parent":"shotung_mover"},{"name":"Shotung_Shoot","parent":"shotung_mover","rotation":-7.45,"x":-252.06,"y":129.03,"scaleX":2.1382,"scaleY":2.1382},{"name":"shotung","parent":"shotung_mover","x":23.87,"y":-30.55},{"name":"shotung_reload","parent":"shotung_mover","x":-74.85,"y":46.94}],"slots":[{"name":"paytable_mask","bone":"root"},{"name":"shotung_back","bone":"shotung_reload","attachment":"shotgun_back_part"},{"name":"shotung","bone":"shotung","attachment":"shotgun"},{"name":"shotung_reload","bone":"shotung_reload","attachment":"shotgun_front_part"},{"name":"shootung_shoot","bone":"Shotung_Shoot"},{"name":"glow","bone":"Shotung_Shoot","blend":"additive"},{"name":"shotung_gilza_0","bone":"Gilza_out"},{"name":"blank","bone":"root"}],"skins":[{"name":"default","attachments":{"shotung_reload":{"shotgun_front_part":{"x":-31.57,"y":16.65,"width":92,"height":92}},"glow":{"shoot_glow":{"x":61.65,"y":-6.05,"rotation":7.45,"width":128,"height":128}},"shootung_shoot":{"shotung_shoot_1":{"width":128,"height":86},"shotung_shoot_2":{"width":128,"height":86},"shotung_shoot_3":{"width":128,"height":86},"shotung_shoot_4":{"width":128,"height":86},"shotung_shoot_5":{"width":128,"height":86},"shotung_shoot_6":{"width":128,"height":86},"shotung_shoot_7":{"width":128,"height":86},"shotung_shoot_8":{"width":128,"height":86}},"shotung_back":{"shotgun_back_part":{"x":-57.97,"y":23.53,"width":64,"height":74}},"blank":{"blank":{"x":-59.63,"y":33.67,"scaleX":60,"scaleY":50,"width":4,"height":4}},"shotung_gilza_0":{"shotung_gilza_0":{"width":70,"height":58},"shotung_gilza_1":{"width":70,"height":58},"shotung_gilza_2":{"width":70,"height":58},"shotung_gilza_3":{"width":70,"height":58},"shotung_gilza_4":{"width":70,"height":58},"shotung_gilza_5":{"width":70,"height":58},"shotung_gilza_6":{"width":70,"height":58},"shotung_gilza_7":{"width":70,"height":58},"shotung_gilza_8":{"width":70,"height":58}},"paytable_mask":{"paytable_mask":{"type":"clipping","end":"paytable_mask","vertexCount":4,"vertices":[-161.57,126.15,-162.86,-59.49,44.93,-59.78,44.65,126.5],"color":"ce3a3aff"}},"shotung":{"shotgun":{"x":-87.25,"y":65.44,"width":208,"height":208}}}}],"animations":{"animation":{"slots":{"shotung_gilza_0":{"color":[{"time":0.4,"color":"ffffffff"},{"time":0.5333,"color":"ffffff00"}],"attachment":[{"name":null},{"time":0.2,"name":null},{"time":0.2333,"name":"shotung_gilza_0"},{"time":0.2667,"name":"shotung_gilza_1"},{"time":0.3,"name":"shotung_gilza_2"},{"time":0.3333,"name":"shotung_gilza_3"},{"time":0.3667,"name":"shotung_gilza_4"},{"time":0.4,"name":"shotung_gilza_5"},{"time":0.4333,"name":"shotung_gilza_6"},{"time":0.4667,"name":"shotung_gilza_7"},{"time":0.5,"name":"shotung_gilza_8"},{"time":0.5333,"name":null}]},"blank":{"attachment":[{"name":null}]},"shootung_shoot":{"attachment":[{"name":null},{"time":0.6667,"name":null},{"time":0.7,"name":"shotung_shoot_1"},{"time":0.7667,"name":"shotung_shoot_2"},{"time":0.8,"name":"shotung_shoot_3"},{"time":0.8333,"name":"shotung_shoot_4"},{"time":0.8667,"name":"shotung_shoot_5"},{"time":0.9,"name":"shotung_shoot_6"},{"time":0.9333,"name":"shotung_shoot_7"},{"time":0.9667,"name":"shotung_shoot_8"},{"time":1,"name":null}]},"paytable_mask":{"attachment":[{"name":null}]},"glow":{"attachment":[{"name":null},{"time":0.6667,"name":null},{"time":0.7,"name":"shoot_glow"},{"time":0.7667,"name":null}]}},"bones":{"root":{"rotate":[{"angle":5.39,"curve":0.162,"c2":0.16,"c3":0.75},{"time":0.2667,"angle":10.07,"curve":0.25,"c3":0.75},{"time":0.5,"angle":6.45,"curve":0.258,"c3":0.619,"c4":0.45},{"time":0.6333,"angle":16.45,"curve":0.25,"c3":0.75},{"time":0.7333,"angle":-1.28,"curve":0.25,"c3":0.75},{"time":1,"angle":5.39}],"translate":[{"x":60.2,"y":-21.9},{"time":0.1667,"x":25.51,"y":-21.94},{"time":0.3333,"x":-19.94,"y":16.59},{"time":0.5,"curve":0.25,"c3":0.75},{"time":0.6333,"x":3.28,"y":-1.68,"curve":0.25,"c3":0.814,"c4":0.78},{"time":0.7333,"x":61,"y":-46.96,"curve":0.2,"c2":0.18,"c3":0.618,"c4":0.44},{"time":1,"x":60.2,"y":-21.9}],"scale":[{"x":0.991,"y":0.991},{"time":0.5,"curve":0.25,"c3":0.75},{"time":0.8333,"x":0.994,"y":0.99,"curve":0.25,"c3":0.75},{"time":1,"x":0.991,"y":0.991}],"shear":[{"x":7},{"time":0.2667,"x":-0.89},{"time":0.5},{"time":0.6,"x":8.06,"curve":0.25,"c3":0.75},{"time":0.7,"x":-9.99,"curve":0.25,"c3":0.75},{"time":1,"x":7}]},"Gilza_out":{"translate":[{"time":0.2},{"time":0.3333,"x":-86.07,"y":192.69},{"time":0.4,"x":-179.72,"y":151.38},{"time":0.5333,"x":-281.07,"y":31.29}],"scale":[{"time":0.2,"x":0.8,"y":0.8}]},"shotung_reload":{"rotate":[{},{"time":0.2,"angle":-4.49},{"time":0.3333,"angle":-1.37},{"time":0.4333,"angle":-2.52},{"time":0.5333,"curve":"stepped"},{"time":0.8667,"curve":"stepped"},{"time":1}],"translate":[{"curve":0.25,"c3":0.75},{"time":0.2,"x":43.4,"y":-32.79,"curve":0.25,"c3":0.75},{"time":0.3333,"x":-8.07,"y":-2.13,"curve":0.25,"c3":0.842,"c4":0.8},{"time":0.4667,"x":9.67,"y":-11.54,"curve":0.19,"c2":0.17,"c3":0.75},{"time":0.6333,"x":-1.35,"y":-0.59,"curve":0.25,"c3":0.75},{"time":0.7333,"x":10.65,"y":-7.6,"curve":0.25,"c3":0.75},{"time":0.8667,"curve":"stepped"},{"time":1}],"scale":[{},{"time":0.2,"x":0.8,"y":0.804},{"time":0.3333,"x":0.994,"y":1.026},{"time":0.5333,"curve":"stepped"},{"time":0.8667,"curve":"stepped"},{"time":1}],"shear":[{},{"time":0.2,"y":11.14},{"time":0.3333,"x":-4.86},{"time":0.5333,"curve":"stepped"},{"time":0.8667,"curve":"stepped"},{"time":1}]}},"drawOrder":[{"offsets":[{"slot":"shotung_gilza_0","offset":-5}]}]},"lose":{"slots":{"shotung_gilza_0":{"attachment":[{"name":null}]},"shotung_reload":{"color":[{"color":"ffffffff"},{"time":0.3333,"color":"605f5fff"}]},"shotung":{"color":[{"color":"ffffffff"},{"time":0.3333,"color":"605f5fff"}]},"blank":{"attachment":[{"name":null}]},"shootung_shoot":{"attachment":[{"name":null}]},"paytable_mask":{"attachment":[{"name":null}]},"glow":{"attachment":[{"name":null}]},"shotung_back":{"color":[{"color":"ffffffff"},{"time":0.3333,"color":"605f5fff"}]}},"bones":{"root":{"rotate":[{"angle":5.39}],"translate":[{"x":60.2,"y":-21.9}],"scale":[{"x":0.991,"y":0.991}],"shear":[{"x":7}]},"shotung_reload":{"rotate":[{}],"translate":[{}],"scale":[{}],"shear":[{}]}},"drawOrder":[{"offsets":[{"slot":"shotung_gilza_0","offset":-5}]}]},"paytable_idle":{"slots":{"shotung_gilza_0":{"attachment":[{"name":null}]},"shotung_reload":{"color":[{"color":"ffffffff"}]},"shotung":{"color":[{"color":"ffffffff"}]},"blank":{"attachment":[{"name":"blank"}]},"shootung_shoot":{"attachment":[{"name":null}]},"paytable_mask":{"attachment":[{"name":"paytable_mask"}]},"glow":{"attachment":[{"name":null}]},"shotung_back":{"color":[{"color":"ffffffff"}]}},"bones":{"root":{"rotate":[{"angle":5.39}],"translate":[{"x":60.2,"y":-21.9}],"scale":[{"x":0.991,"y":0.991}],"shear":[{"x":7}]},"shotung_reload":{"rotate":[{}],"translate":[{}],"scale":[{}],"shear":[{}]}},"drawOrder":[{"offsets":[{"slot":"shotung_gilza_0","offset":-5}]}]},"static":{"slots":{"shotung_gilza_0":{"attachment":[{"name":null}]},"shotung_reload":{"color":[{"color":"ffffffff"}]},"shotung":{"color":[{"color":"ffffffff"}]},"blank":{"attachment":[{"name":"blank"}]},"shootung_shoot":{"attachment":[{"name":null}]},"paytable_mask":{"attachment":[{"name":"paytable_mask"}]},"glow":{"attachment":[{"name":null}]},"shotung_back":{"color":[{"color":"ffffffff"}]}},"bones":{"root":{"rotate":[{"angle":5.39}],"translate":[{"x":60.2,"y":-21.9}],"scale":[{"x":0.991,"y":0.991}],"shear":[{"x":7}]},"shotung_reload":{"rotate":[{}],"translate":[{}],"scale":[{}],"shear":[{}]}},"drawOrder":[{"offsets":[{"slot":"shotung_gilza_0","offset":-5}]}]}}}